KratosMultiphysics/CompressiblePotentialFlowApplication/MainKratos.py
KratosMultiphysics/CompressiblePotentialFlowApplication/__init__.py
KratosMultiphysics/CompressiblePotentialFlowApplication/ale_potential_flow_solver.py
KratosMultiphysics/CompressiblePotentialFlowApplication/apply_far_field_and_wake_process.py
KratosMultiphysics/CompressiblePotentialFlowApplication/apply_potential_flow_hessian_remeshing_process.py
KratosMultiphysics/CompressiblePotentialFlowApplication/compute_embedded_lift_process.py
KratosMultiphysics/CompressiblePotentialFlowApplication/compute_forces_on_nodes_process.py
KratosMultiphysics/CompressiblePotentialFlowApplication/compute_lift_process.py
KratosMultiphysics/CompressiblePotentialFlowApplication/compute_nodal_value_process.py
KratosMultiphysics/CompressiblePotentialFlowApplication/define_embedded_wake_process_2d.py
KratosMultiphysics/CompressiblePotentialFlowApplication/level_set_remeshing_process.py
KratosMultiphysics/CompressiblePotentialFlowApplication/placeholder_process.py
KratosMultiphysics/CompressiblePotentialFlowApplication/potential_flow_adjoint_solver.py
KratosMultiphysics/CompressiblePotentialFlowApplication/potential_flow_analysis.py
KratosMultiphysics/CompressiblePotentialFlowApplication/potential_flow_response.py
KratosMultiphysics/CompressiblePotentialFlowApplication/potential_flow_response_function_factory.py
KratosMultiphysics/CompressiblePotentialFlowApplication/potential_flow_solver.py
KratosMultiphysics/CompressiblePotentialFlowApplication/python_solvers_wrapper_compressible_potential.py
KratosMultiphysics/CompressiblePotentialFlowApplication/stochastic_potential_flow_response.py
KratosMultiphysics/.libs/KratosCompressiblePotentialFlowApplication.pyd
KratosMultiphysics/.libs/KratosCompressiblePotentialFlowCore.dll
KratosMultiphysics/.libs/KratosCompressiblePotentialFlowCore.lib
kratoscompressiblepotentialflowapplication-10.4.0.dist-info/METADATA
kratoscompressiblepotentialflowapplication-10.4.0.dist-info/WHEEL
kratoscompressiblepotentialflowapplication-10.4.0.dist-info/RECORD
